{"layer":"monster","index":100,"direction":6,"slotWidth":140,"slotHeight":140,"actions":{"standing":{"interval":500,"frames":[{"slot":0,"srcFrame":24,"w":116,"h":100,"offsetX":-18,"offsetY":-70},{"slot":1,"srcFrame":25,"w":116,"h":100,"offsetX":-18,"offsetY":-70},{"slot":2,"srcFrame":26,"w":120,"h":100,"offsetX":-18,"offsetY":-70},{"slot":3,"srcFrame":27,"w":120,"h":100,"offsetX":-18,"offsetY":-70}]},"walking":{"interval":100,"frames":[{"slot":4,"srcFrame":68,"w":128,"h":100,"offsetX":-24,"offsetY":-70},{"slot":5,"srcFrame":69,"w":112,"h":100,"offsetX":-37,"offsetY":-72},{"slot":6,"srcFrame":70,"w":116,"h":100,"offsetX":-38,"offsetY":-72},{"slot":7,"srcFrame":71,"w":112,"h":96,"offsetX":-35,"offsetY":-69},{"slot":8,"srcFrame":72,"w":112,"h":100,"offsetX":-38,"offsetY":-72},{"slot":9,"srcFrame":73,"w":116,"h":100,"offsetX":-36,"offsetY":-72}]},"attack1":{"interval":100,"frames":[{"slot":10,"srcFrame":116,"w":80,"h":136,"offsetX":-6,"offsetY":-104},{"slot":11,"srcFrame":117,"w":96,"h":140,"offsetX":-6,"offsetY":-108},{"slot":12,"srcFrame":118,"w":124,"h":140,"offsetX":-7,"offsetY":-107},{"slot":13,"srcFrame":119,"w":128,"h":140,"offsetX":-9,"offsetY":-106},{"slot":14,"srcFrame":120,"w":140,"h":96,"offsetX":-61,"offsetY":-62},{"slot":15,"srcFrame":121,"w":128,"h":96,"offsetX":-59,"offsetY":-64}]},"struck":{"interval":200,"frames":[{"slot":16,"srcFrame":140,"w":100,"h":100,"offsetX":-9,"offsetY":-69},{"slot":17,"srcFrame":141,"w":128,"h":96,"offsetX":-24,"offsetY":-66}]},"die":{"interval":100,"frames":[{"slot":18,"srcFrame":204,"w":124,"h":100,"offsetX":-21,"offsetY":-68},{"slot":19,"srcFrame":205,"w":128,"h":96,"offsetX":-22,"offsetY":-67},{"slot":20,"srcFrame":206,"w":128,"h":96,"offsetX":-24,"offsetY":-66},{"slot":21,"srcFrame":207,"w":128,"h":100,"offsetX":-27,"offsetY":-68},{"slot":22,"srcFrame":208,"w":132,"h":100,"offsetX":-36,"offsetY":-70},{"slot":23,"srcFrame":209,"w":100,"h":100,"offsetX":-40,"offsetY":-66},{"slot":24,"srcFrame":210,"w":104,"h":96,"offsetX":-46,"offsetY":-51},{"slot":25,"srcFrame":211,"w":112,"h":80,"offsetX":-55,"offsetY":-21},{"slot":26,"srcFrame":212,"w":108,"h":72,"offsetX":-53,"offsetY":-3},{"slot":27,"srcFrame":213,"w":108,"h":80,"offsetX":-53,"offsetY":-2}]},"dead":{"interval":1000,"frames":[{"slot":28,"srcFrame":213,"w":108,"h":80,"offsetX":-53,"offsetY":-2}]},"revive":{"interval":100,"frames":[{"slot":29,"srcFrame":144,"w":92,"h":100,"offsetX":-4,"offsetY":-63},{"slot":30,"srcFrame":143,"w":100,"h":88,"offsetX":-3,"offsetY":-59},{"slot":31,"srcFrame":142,"w":100,"h":100,"offsetX":1,"offsetY":-71},{"slot":32,"srcFrame":141,"w":128,"h":96,"offsetX":-24,"offsetY":-66},{"slot":33,"srcFrame":140,"w":100,"h":100,"offsetX":-9,"offsetY":-69},{"slot":34,"srcFrame":139,"w":128,"h":104,"offsetX":-39,"offsetY":-70},{"slot":35,"srcFrame":138,"w":96,"h":104,"offsetX":-17,"offsetY":-70},{"slot":36,"srcFrame":137,"w":112,"h":116,"offsetX":-22,"offsetY":-70},{"slot":37,"srcFrame":136,"w":96,"h":104,"offsetX":-7,"offsetY":-65},{"slot":38,"srcFrame":135,"w":92,"h":128,"offsetX":-13,"offsetY":-70}]}}}