{"layer":"monster","index":117,"direction":2,"slotWidth":228,"slotHeight":220,"actions":{"show":{"interval":100,"frames":[{"slot":0,"srcFrame":216,"w":228,"h":220,"offsetX":-80,"offsetY":-146},{"slot":1,"srcFrame":217,"w":208,"h":208,"offsetX":-76,"offsetY":-136},{"slot":2,"srcFrame":218,"w":176,"h":172,"offsetX":-58,"offsetY":-121},{"slot":3,"srcFrame":219,"w":108,"h":108,"offsetX":-24,"offsetY":-86},{"slot":4,"srcFrame":220,"w":72,"h":96,"offsetX":-7,"offsetY":-62},{"slot":5,"srcFrame":221,"w":64,"h":96,"offsetX":-7,"offsetY":-69},{"slot":6,"srcFrame":222,"w":68,"h":112,"offsetX":1,"offsetY":-82},{"slot":7,"srcFrame":223,"w":68,"h":112,"offsetX":0,"offsetY":-83},{"slot":8,"srcFrame":224,"w":68,"h":108,"offsetX":0,"offsetY":-82},{"slot":9,"srcFrame":225,"w":68,"h":104,"offsetX":0,"offsetY":-81}]},"standing":{"interval":500,"frames":[{"slot":10,"srcFrame":8,"w":48,"h":108,"offsetX":4,"offsetY":-85},{"slot":11,"srcFrame":9,"w":56,"h":112,"offsetX":-2,"offsetY":-85},{"slot":12,"srcFrame":10,"w":52,"h":108,"offsetX":1,"offsetY":-85},{"slot":13,"srcFrame":11,"w":52,"h":108,"offsetX":-1,"offsetY":-85}]},"walking":{"interval":100,"frames":[{"slot":14,"srcFrame":44,"w":60,"h":108,"offsetX":-6,"offsetY":-85},{"slot":15,"srcFrame":45,"w":60,"h":108,"offsetX":-8,"offsetY":-85},{"slot":16,"srcFrame":46,"w":64,"h":112,"offsetX":-12,"offsetY":-85},{"slot":17,"srcFrame":47,"w":68,"h":108,"offsetX":-15,"offsetY":-85},{"slot":18,"srcFrame":48,"w":64,"h":112,"offsetX":-10,"offsetY":-85},{"slot":19,"srcFrame":49,"w":64,"h":108,"offsetX":-9,"offsetY":-85}]},"attack1":{"interval":100,"frames":[{"slot":20,"srcFrame":92,"w":64,"h":112,"offsetX":-11,"offsetY":-85},{"slot":21,"srcFrame":93,"w":56,"h":112,"offsetX":-7,"offsetY":-82},{"slot":22,"srcFrame":94,"w":52,"h":112,"offsetX":-2,"offsetY":-85},{"slot":23,"srcFrame":95,"w":48,"h":108,"offsetX":5,"offsetY":-85},{"slot":24,"srcFrame":96,"w":68,"h":108,"offsetX":-10,"offsetY":-85},{"slot":25,"srcFrame":97,"w":64,"h":112,"offsetX":-5,"offsetY":-85}]},"struck":{"interval":200,"frames":[{"slot":26,"srcFrame":132,"w":56,"h":96,"offsetX":0,"offsetY":-68},{"slot":27,"srcFrame":133,"w":48,"h":100,"offsetX":1,"offsetY":-75}]},"die":{"interval":100,"frames":[{"slot":28,"srcFrame":162,"w":68,"h":108,"offsetX":-10,"offsetY":-83},{"slot":29,"srcFrame":163,"w":56,"h":108,"offsetX":-2,"offsetY":-84},{"slot":30,"srcFrame":164,"w":56,"h":108,"offsetX":-3,"offsetY":-90},{"slot":31,"srcFrame":165,"w":56,"h":108,"offsetX":-6,"offsetY":-93},{"slot":32,"srcFrame":166,"w":56,"h":108,"offsetX":-8,"offsetY":-94},{"slot":33,"srcFrame":167,"w":56,"h":112,"offsetX":-10,"offsetY":-86},{"slot":34,"srcFrame":168,"w":76,"h":128,"offsetX":-21,"offsetY":-93},{"slot":35,"srcFrame":169,"w":92,"h":140,"offsetX":-23,"offsetY":-98},{"slot":36,"srcFrame":170,"w":96,"h":136,"offsetX":-19,"offsetY":-93}]},"revive":{"interval":100,"frames":[{"slot":37,"srcFrame":144,"w":92,"h":100,"offsetX":-21,"offsetY":-72},{"slot":38,"srcFrame":143,"w":80,"h":96,"offsetX":-16,"offsetY":-63},{"slot":39,"srcFrame":142,"w":76,"h":96,"offsetX":-15,"offsetY":-66},{"slot":40,"srcFrame":141,"w":44,"h":104,"offsetX":3,"offsetY":-73},{"slot":41,"srcFrame":140,"w":60,"h":92,"offsetX":-10,"offsetY":-69},{"slot":42,"srcFrame":139,"w":52,"h":104,"offsetX":-3,"offsetY":-76},{"slot":43,"srcFrame":138,"w":56,"h":100,"offsetX":-6,"offsetY":-71},{"slot":44,"srcFrame":137,"w":80,"h":92,"offsetX":-15,"offsetY":-69},{"slot":45,"srcFrame":136,"w":72,"h":92,"offsetX":-12,"offsetY":-67}]}},"overlays":{"show":{"interval":100,"frames":[{"slot":46,"srcFrame":-1,"w":0,"h":0,"offsetX":0,"offsetY":0,"empty":true},{"slot":47,"srcFrame":-1,"w":0,"h":0,"offsetX":0,"offsetY":0,"empty":true},{"slot":48,"srcFrame":-1,"w":0,"h":0,"offsetX":0,"offsetY":0,"empty":true},{"slot":49,"srcFrame":-1,"w":0,"h":0,"offsetX":0,"offsetY":0,"empty":true},{"slot":50,"srcFrame":-1,"w":0,"h":0,"offsetX":0,"offsetY":0,"empty":true},{"slot":51,"srcFrame":418,"w":44,"h":60,"offsetX":2,"offsetY":-57},{"slot":52,"srcFrame":419,"w":40,"h":68,"offsetX":10,"offsetY":-66},{"slot":53,"srcFrame":420,"w":44,"h":72,"offsetX":10,"offsetY":-67},{"slot":54,"srcFrame":421,"w":44,"h":68,"offsetX":9,"offsetY":-66},{"slot":55,"srcFrame":422,"w":44,"h":68,"offsetX":7,"offsetY":-65}]},"standing":{"interval":500,"frames":[{"slot":56,"srcFrame":234,"w":56,"h":100,"offsetX":12,"offsetY":-69},{"slot":57,"srcFrame":235,"w":56,"h":100,"offsetX":12,"offsetY":-69},{"slot":58,"srcFrame":236,"w":56,"h":100,"offsetX":12,"offsetY":-69},{"slot":59,"srcFrame":237,"w":60,"h":100,"offsetX":9,"offsetY":-69}]},"walking":{"interval":100,"frames":[{"slot":60,"srcFrame":270,"w":68,"h":100,"offsetX":4,"offsetY":-69},{"slot":61,"srcFrame":271,"w":68,"h":100,"offsetX":3,"offsetY":-69},{"slot":62,"srcFrame":272,"w":72,"h":100,"offsetX":-1,"offsetY":-68},{"slot":63,"srcFrame":273,"w":68,"h":100,"offsetX":-1,"offsetY":-68},{"slot":64,"srcFrame":274,"w":68,"h":100,"offsetX":1,"offsetY":-68},{"slot":65,"srcFrame":275,"w":64,"h":100,"offsetX":4,"offsetY":-69}]},"attack1":{"interval":100,"frames":[{"slot":66,"srcFrame":318,"w":52,"h":100,"offsetX":15,"offsetY":-69},{"slot":67,"srcFrame":319,"w":52,"h":100,"offsetX":13,"offsetY":-68},{"slot":68,"srcFrame":320,"w":52,"h":100,"offsetX":13,"offsetY":-70},{"slot":69,"srcFrame":321,"w":56,"h":104,"offsetX":11,"offsetY":-69},{"slot":70,"srcFrame":322,"w":76,"h":104,"offsetX":1,"offsetY":-69},{"slot":71,"srcFrame":323,"w":68,"h":104,"offsetX":4,"offsetY":-70}]},"struck":{"interval":200,"frames":[{"slot":72,"srcFrame":358,"w":64,"h":88,"offsetX":11,"offsetY":-59},{"slot":73,"srcFrame":359,"w":60,"h":92,"offsetX":12,"offsetY":-64}]},"die":{"interval":100,"frames":[{"slot":74,"srcFrame":382,"w":72,"h":100,"offsetX":1,"offsetY":-68},{"slot":75,"srcFrame":383,"w":64,"h":96,"offsetX":8,"offsetY":-68},{"slot":76,"srcFrame":384,"w":60,"h":96,"offsetX":10,"offsetY":-72},{"slot":77,"srcFrame":385,"w":64,"h":100,"offsetX":5,"offsetY":-74},{"slot":78,"srcFrame":386,"w":64,"h":100,"offsetX":4,"offsetY":-74},{"slot":79,"srcFrame":387,"w":60,"h":96,"offsetX":3,"offsetY":-68},{"slot":80,"srcFrame":388,"w":84,"h":84,"offsetX":-3,"offsetY":-63},{"slot":81,"srcFrame":-1,"w":0,"h":0,"offsetX":0,"offsetY":0,"empty":true},{"slot":82,"srcFrame":-1,"w":0,"h":0,"offsetX":0,"offsetY":0,"empty":true}]}}}