{"layer":"monster","index":26,"direction":6,"slotWidth":212,"slotHeight":148,"actions":{"standing":{"interval":500,"frames":[{"slot":0,"srcFrame":24,"w":96,"h":92,"offsetX":-10,"offsetY":-55},{"slot":1,"srcFrame":25,"w":100,"h":92,"offsetX":-11,"offsetY":-55},{"slot":2,"srcFrame":26,"w":96,"h":92,"offsetX":-10,"offsetY":-55},{"slot":3,"srcFrame":27,"w":96,"h":92,"offsetX":-9,"offsetY":-55}]},"walking":{"interval":100,"frames":[{"slot":4,"srcFrame":68,"w":140,"h":92,"offsetX":-8,"offsetY":-57},{"slot":5,"srcFrame":69,"w":132,"h":92,"offsetX":-7,"offsetY":-57},{"slot":6,"srcFrame":70,"w":132,"h":96,"offsetX":-9,"offsetY":-58},{"slot":7,"srcFrame":71,"w":140,"h":96,"offsetX":-8,"offsetY":-57},{"slot":8,"srcFrame":72,"w":128,"h":92,"offsetX":-7,"offsetY":-57},{"slot":9,"srcFrame":73,"w":140,"h":92,"offsetX":-8,"offsetY":-59}]},"attack1":{"interval":100,"frames":[{"slot":10,"srcFrame":116,"w":116,"h":124,"offsetX":-30,"offsetY":-75},{"slot":11,"srcFrame":117,"w":192,"h":128,"offsetX":-53,"offsetY":-92},{"slot":12,"srcFrame":118,"w":212,"h":148,"offsetX":-49,"offsetY":-118},{"slot":13,"srcFrame":119,"w":132,"h":116,"offsetX":-75,"offsetY":-81},{"slot":14,"srcFrame":120,"w":116,"h":100,"offsetX":-53,"offsetY":-64},{"slot":15,"srcFrame":121,"w":116,"h":112,"offsetX":-55,"offsetY":-70}]},"struck":{"interval":200,"frames":[{"slot":16,"srcFrame":140,"w":144,"h":112,"offsetX":-29,"offsetY":-54},{"slot":17,"srcFrame":141,"w":116,"h":124,"offsetX":-12,"offsetY":-57}]},"die":{"interval":100,"frames":[{"slot":18,"srcFrame":204,"w":116,"h":104,"offsetX":-14,"offsetY":-57},{"slot":19,"srcFrame":205,"w":152,"h":112,"offsetX":-34,"offsetY":-65},{"slot":20,"srcFrame":206,"w":164,"h":144,"offsetX":-29,"offsetY":-70},{"slot":21,"srcFrame":207,"w":152,"h":132,"offsetX":-12,"offsetY":-90},{"slot":22,"srcFrame":208,"w":164,"h":128,"offsetX":-4,"offsetY":-90},{"slot":23,"srcFrame":209,"w":136,"h":120,"offsetX":0,"offsetY":-85},{"slot":24,"srcFrame":210,"w":124,"h":132,"offsetX":1,"offsetY":-77},{"slot":25,"srcFrame":211,"w":108,"h":128,"offsetX":0,"offsetY":-50},{"slot":26,"srcFrame":212,"w":100,"h":116,"offsetX":-9,"offsetY":-18},{"slot":27,"srcFrame":213,"w":96,"h":124,"offsetX":-8,"offsetY":-27}]},"dead":{"interval":1000,"frames":[{"slot":28,"srcFrame":213,"w":96,"h":124,"offsetX":-8,"offsetY":-27}]},"revive":{"interval":100,"frames":[{"slot":29,"srcFrame":204,"w":116,"h":104,"offsetX":-14,"offsetY":-57},{"slot":30,"srcFrame":205,"w":152,"h":112,"offsetX":-34,"offsetY":-65},{"slot":31,"srcFrame":206,"w":164,"h":144,"offsetX":-29,"offsetY":-70},{"slot":32,"srcFrame":207,"w":152,"h":132,"offsetX":-12,"offsetY":-90},{"slot":33,"srcFrame":208,"w":164,"h":128,"offsetX":-4,"offsetY":-90},{"slot":34,"srcFrame":209,"w":136,"h":120,"offsetX":0,"offsetY":-85},{"slot":35,"srcFrame":210,"w":124,"h":132,"offsetX":1,"offsetY":-77},{"slot":36,"srcFrame":211,"w":108,"h":128,"offsetX":0,"offsetY":-50},{"slot":37,"srcFrame":212,"w":100,"h":116,"offsetX":-9,"offsetY":-18},{"slot":38,"srcFrame":213,"w":96,"h":124,"offsetX":-8,"offsetY":-27}]}}}
